tweetpy/__init__.py
tweetpy/driver.py
tweetpy/twitter.py
tweetpy_janmarkuslanger-0.0.3.dist-info/LICENSE
tweetpy_janmarkuslanger-0.0.3.dist-info/METADATA
tweetpy_janmarkuslanger-0.0.3.dist-info/WHEEL
tweetpy_janmarkuslanger-0.0.3.dist-info/top_level.txt
tweetpy_janmarkuslanger-0.0.3.dist-info/RECORD
